datasette_hovercards/__init__.py
datasette_hovercards/static/datasette-hovercards.js
datasette_hovercards-0.1a0.dist-info/METADATA
datasette_hovercards-0.1a0.dist-info/WHEEL
datasette_hovercards-0.1a0.dist-info/entry_points.txt
datasette_hovercards-0.1a0.dist-info/top_level.txt
datasette_hovercards-0.1a0.dist-info/RECORD
