Metadata-Version: 2.1
Name: datasette-hovercards
Version: 0.1a0
Summary: Add preview hovercards to links in Datasette
Home-page: https://github.com/simonw/datasette-hovercards
Author: Simon Willison
License: Apache License, Version 2.0
Project-URL: Issues, https://github.com/simonw/datasette-hovercards/issues
Project-URL: CI, https://github.com/simonw/datasette-hovercards/actions
Project-URL: Changelog, https://github.com/simonw/datasette-hovercards/releases
Platform: UNKNOWN
Classifier: Framework :: Datasette
Classifier: License :: OSI Approved :: Apache Software License
Requires-Python: >=3.6
Requires-Dist: datasette
Provides-Extra: test
Requires-Dist: pytest ; extra == 'test'
Requires-Dist: pytest-asyncio ; extra == 'test'
